motif_broker_request/__init__.py
motif_broker_request/request.py
motif_broker_request-1.0.0.dist-info/METADATA
motif_broker_request-1.0.0.dist-info/WHEEL
motif_broker_request-1.0.0.dist-info/top_level.txt
motif_broker_request-1.0.0.dist-info/RECORD
