Metadata-Version: 2.1
Name: motif-broker-request
Version: 1.0.0
Summary: Package to interrogate motif-broker JS microservice with python
Home-page: https://github.com/MMSB-MOBI/motif-broker-request
Author: Cécile Hilpert
Author-email: cecile.hilpert@ibcp.fr
License: UNKNOWN
Platform: UNKNOWN
Requires-Dist: requests
